Workbook

Sheet Raw Data
A1: Product type | B1: SKU | C1: Price | D1: Availability | E1: Number of products sold | F1: Revenue generated | G1: Customer demographics | H1: Stock levels | I1: Lead times | J1: Order quantities | K1: Shipping times | L1: Shipping carriers | M1: Shipping costs | N1: Supplier name | O1: Location | P1: Lead time | Q1: Production volumes | R1: Manufacturing lead time | S1: Manufacturing costs | T1: Inspection results | U1: Defect rates | V1: Transportation modes | W1: Routes | X1: Costs
A2: haircare | B2: SKU0 | C2: 69.808006 | D2: 55 | E2: 802 | F2: 8661.9968 | G2: Non-binary | H2: 58 | I2: 7 | J2: 96 | K2: 4 | L2: Carrier B | M2: 2.9565721 | N2: Supplier 3 | O2: Mumbai | P2: 29 | Q2: 215 | R2: 29 | S2: 46.279879 | T2: Pending | U2: 0.0022641036 | V2: Road | W2: Route B | X2: 187.75208
A3: skincare | B3: SKU1 | C3: 14.843523 | D3: 95 | E3: 736 | F3: 7460.9001 | G3: Female | H3: 53 | I3: 30 | J3: 37 | K3: 2 | L3: Carrier A | M3: 9.7165748 | N3: Supplier 3 | O3: Mumbai | P3: 23 | Q3: 517 | R3: 30 | S3: 33.616769 | T3: Pending | U3: 0.04854068 | V3: Road | W3: Route B | X3: 503.06558
A4: haircare | B4: SKU2 | C4: 11.319683 | D4: 34 | E4: 8 | F4: 9577.7496 | G4: Unknown | H4: 1 | I4: 10 | J4: 88 | K4: 2 | L4: Carrier B | M4: 8.0544793 | N4: Supplier 1 | O4: Mumbai | P4: 12 | Q4: 971 | R4: 27 | S4: 30.688019 | T4: Pending | U4: 0.045805926 | V4: Air | W4: Route C | X4: 141.92028
A5: skincare | B5: SKU3 | C5: 61.163343 | D5: 68 | E5: 83 | F5: 7766.8364 | G5: Non-binary | H5: 23 | I5: 13 | J5: 59 | K5: 6 | L5: Carrier C | M5: 1.7295686 | N5: Supplier 5 | O5: Kolkata | P5: 24 | Q5: 937 | R5: 18 | S5: 35.624741 | T5: Fail | U5: 0.047466486 | V5: Rail | W5: Route A | X5: 254.77616
A6: skincare | B6: SKU4 | C6: 4.805496 | D6: 26 | E6: 871 | F6: 2686.5052 | G6: Non-binary | H6: 5 | I6: 3 | J6: 56 | K6: 8 | L6: Carrier A | M6: 3.8905479 | N6: Supplier 1 | O6: Delhi | P6: 5 | Q6: 414 | R6: 3 | S6: 92.065161 | T6: Fail | U6: 0.031455795 | V6: Air | W6: Route A | X6: 923.44063
A7: haircare | B7: SKU5 | C7: 1.699976 | D7: 87 | E7: 147 | F7: 2828.3487 | G7: Non-binary | H7: 90 | I7: 27 | J7: 66 | K7: 3 | L7: Carrier B | M7: 4.4440989 | N7: Supplier 4 | O7: Bangalore | P7: 10 | Q7: 104 | R7: 17 | S7: 56.766476 | T7: Fail | U7: 0.027791935 | V7: Road | W7: Route A | X7: 235.46124
A8: skincare | B8: SKU6 | C8: 4.0783329 | D8: 48 | E8: 65 | F8: 7823.4766 | G8: Male | H8: 11 | I8: 15 | J8: 58 | K8: 8 | L8: Carrier C | M8: 3.8807633 | N8: Supplier 3 | O8: Kolkata | P8: 14 | Q8: 314 | R8: 24 | S8: 1.0850686 | T8: Pending | U8: 0.010009106 | V8: Sea | W8: Route A | X8: 134.3691
A9: cosmetics | B9: SKU7 | C9: 42.958384 | D9: 59 | E9: 426 | F9: 8496.1038 | G9: Female | H9: 93 | I9: 17 | J9: 11 | K9: 1 | L9: Carrier B | M9: 2.3483388 | N9: Supplier 4 | O9: Bangalore | P9: 22 | Q9: 564 | R9: 1 | S9: 99.466109 | T9: Fail | U9: 0.0039817719 | V9: Road | W9: Route C | X9: 802.05631
A10: cosmetics | B10: SKU8 | C10: 68.717597 | D10: 78 | E10: 150 | F10: 7517.3632 | G10: Female | H10: 5 | I10: 10 | J10: 15 | K10: 7 | L10: Carrier C | M10: 3.4047339 | N10: Supplier 4 | O10: Mumbai | P10: 13 | Q10: 769 | R10: 8 | S10: 11.423027 | T10: Pending | U10: 0.027098627 | V10: Sea | W10: Route B | X10: 505.55713
A11: skincare | B11: SKU9 | C11: 64.015733 | D11: 35 | E11: 980 | F11: 4971.146 | G11: Unknown | H11: 14 | I11: 27 | J11: 83 | K11: 1 | L11: Carrier A | M11: 7.1666453 | N11: Supplier 2 | O11: Chennai | P11: 29 | Q11: 963 | R11: 23 | S11: 47.957602 | T11: Pending | U11: 0.038446145 | V11: Rail | W11: Route B | X11: 995.92946
A12: skincare | B12: SKU10 | C12: 15.707796 | D12: 11 | E12: 996 | F12: 2330.9658 | G12: Non-binary | H12: 51 | I12: 13 | J12: 80 | K12: 2 | L12: Carrier C | M12: 8.6732112 | N12: Supplier 5 | O12: Kolkata | P12: 18 | Q12: 830 | R12: 5 | S12: 96.527353 | T12: Pass | U12: 0.017273139 | V12: Road | W12: Route B | X12: 806.10318
A13: skincare | B13: SKU11 | C13: 90.63546 | D13: 95 | E13: 960 | F13: 6099.9441 | G13: Female | H13: 46 | I13: 23 | J13: 60 | K13: 1 | L13: Carrier A | M13: 4.5239431 | N13: Supplier 2 | O13: Kolkata | P13: 28 | Q13: 362 | R13: 11 | S13: 27.592363 | T13: Pending | U13: 0.00021169821 | V13: Air | W13: Route A | X13: 126.72303
... A101: haircare | B101: SKU99 | C101: 68.517833 | D101: 17 | E101: 627 | F101: 9185.1858 | G101: Unknown | H101: 55 | I101: 8 | J101: 59 | K101: 6 | L101: Carrier B | M101: 1.3110238 | N101: Supplier 2 | O101: Chennai | P101: 29 | Q101: 921 | R101: 2 | S101: 38.072899 | T101: Fail | U101: 0.0034602729 | V101: Rail | W101: Route B | X101: 210.74301

Sheet Revenue by Product
A1: Revenue & Sales Performance by Product Type
A2: Formulas used: SUMIF | AVERAGEIF | COUNTIF | Derived: Revenue Share = Group Revenue / SUM(All Revenue)
J3: Formula Reference
A4: Product Type | B4: No. of SKUs | C4: Units Sold | D4: Revenue ($) | E4: Revenue Share (%) | F4: Avg Price ($) | G4: Avg Defect Rate (%) | H4: Avg Lead Time (days) | J4: B5 | K4: =COUNTIF(RawData[Product type], A5) -> 26
A5: cosmetics | B5: =COUNTIF(RawData[Product type],A5) -> 26 | C5: =SUMIF(RawData[Product type],A5,RawData[Number of products sold]) -> 11757 | D5: =SUMIF(RawData[Product type],A5,RawData[Revenue generated]) -> 161521.27 | E5: =D5/SUM($D$5:$D$7) -> 0.27963975 | F5: =AVERAGEIF(RawData[Product type],A5,RawData[Price]) -> 57.361058 | G5: =AVERAGEIF(RawData[Product type],A5,RawData[Defect rates])/100 -> 0.0001919287 | H5: =AVERAGEIF(RawData[Product type],A5,RawData[Lead times]) -> 15.384615 | J5: C5 | K5: =SUMIF(RawData[Product type], A5, RawData[Number of products sold]) -> 11757
A6: haircare | B6: =COUNTIF(RawData[Product type],A6) -> 34 | C6: =SUMIF(RawData[Product type],A6,RawData[Number of products sold]) -> 13611 | D6: =SUMIF(RawData[Product type],A6,RawData[Revenue generated]) -> 174455.39 | E6: =D6/SUM($D$5:$D$7) -> 0.30203244 | F6: =AVERAGEIF(RawData[Product type],A6,RawData[Price]) -> 46.014279 | G6: =AVERAGEIF(RawData[Product type],A6,RawData[Defect rates])/100 -> 0.00024831502 | H6: =AVERAGEIF(RawData[Product type],A6,RawData[Lead times]) -> 15.529412 | J6: D5 | K6: =SUMIF(RawData[Product type], A5, RawData[Revenue generated]) -> 161521.27
A7: skincare | B7: =COUNTIF(RawData[Product type],A7) -> 40 | C7: =SUMIF(RawData[Product type],A7,RawData[Number of products sold]) -> 20731 | D7: =SUMIF(RawData[Product type],A7,RawData[Revenue generated]) -> 241628.16 | E7: =D7/SUM($D$5:$D$7) -> 0.41832782 | F7: =AVERAGEIF(RawData[Product type],A7,RawData[Price]) -> 47.259329 | G7: =AVERAGEIF(RawData[Product type],A7,RawData[Defect rates])/100 -> 0.00023346808 | H7: =AVERAGEIF(RawData[Product type],A7,RawData[Lead times]) -> 16.7 | J7: E5 | K7: D5/SUM($D$5:$D$7) <- locked denominator
A8: TOTAL | B8: =SUM(B5:B7) -> 100 | C8: =SUM(C5:C7) -> 46099 | D8: =SUM(D5:D7) -> 577604.82 | E8: =SUM(E5:E7) -> 1 | F8: =AVERAGE(F5:F7) -> 50.211555 | G8: =AVERAGE(G5:G7) -> 0.0002245706 | H8: =AVERAGE(H5:H7) -> 15.871342 | J8: F5 | K8: =AVERAGEIF(RawData[Product type], A5, RawData[Price]) -> 57.361058
J9: G5 | K9: =AVERAGEIF(RawData[Product type], A5, RawData[Defect rates]) / 100 -> 0.0001919287
J10: H5 | K10: =AVERAGEIF(RawData[Product type], A5, RawData[Lead times]) -> 15.384615

Sheet Supplier Performance
A1: Supplier Performance Dashboard
A2: Formulas: AVERAGEIF | SUMIF | COUNTIFS (two-criteria) — Pass Rate = COUNTIFS(Supplier, Pass) / COUNTIF(Supplier)
K3: Formula Reference
A4: Supplier | B4: SKUs | C4: Avg Lead Time (days) | D4: Avg Mfg Lead (days) | E4: Avg Mfg Cost ($) | F4: Avg Defect Rate (%) | G4: Total Production | H4: Insp. Pass Rate (%) | I4: Insp. Fail Rate (%) | K4: B5 | L4: =COUNTIF(RawData[Supplier name], A5) -> 27
A5: Supplier 1 | B5: =COUNTIF(RawData[Supplier name],A5) -> 27 | C5: =AVERAGEIF(RawData[Supplier name],A5,RawData[Lead time]) -> 14.777778 | D5: =AVERAGEIF(RawData[Supplier name],A5,RawData[Manufacturing lead time]) -> 12.592593 | E5: =AVERAGEIF(RawData[Supplier name],A5,RawData[Manufacturing costs]) -> 45.254027 | F5: =AVERAGEIF(RawData[Supplier name],A5,RawData[Defect rates])/100 -> 0.00018036297 | G5: =SUMIF(RawData[Supplier name],A5,RawData[Production volumes]) -> 13545 | H5: =COUNTIFS(RawData[Supplier name],A5,RawData[Inspection results],"Pass")/COUNTIF(RawData[Supplier name],A5) -> 0.48148148 | I5: =COUNTIFS(RawData[Supplier name],A5,RawData[Inspection results],"Fail")/COUNTIF(RawData[Supplier name],A5) -> 0.22222222 | K5: C5 | L5: =AVERAGEIF(RawData[Supplier name], A5, RawData[Lead time]) -> 14.777778
A6: Supplier 2 | B6: =COUNTIF(RawData[Supplier name],A6) -> 22 | C6: =AVERAGEIF(RawData[Supplier name],A6,RawData[Lead time]) -> 18.545455 | D6: =AVERAGEIF(RawData[Supplier name],A6,RawData[Manufacturing lead time]) -> 15.590909 | E6: =AVERAGEIF(RawData[Supplier name],A6,RawData[Manufacturing costs]) -> 41.622514 | F6: =AVERAGEIF(RawData[Supplier name],A6,RawData[Defect rates])/100 -> 0.00023627501 | G6: =SUMIF(RawData[Supplier name],A6,RawData[Production volumes]) -> 14105 | H6: =COUNTIFS(RawData[Supplier name],A6,RawData[Inspection results],"Pass")/COUNTIF(RawData[Supplier name],A6) -> 0.22727273 | I6: =COUNTIFS(RawData[Supplier name],A6,RawData[Inspection results],"Fail")/COUNTIF(RawData[Supplier name],A6) -> 0.36363636 | K6: E5 | L6: =AVERAGEIF(RawData[Supplier name], A5, RawData[Manufacturing costs]) -> 45.254027
A7: Supplier 3 | B7: =COUNTIF(RawData[Supplier name],A7) -> 15 | C7: =AVERAGEIF(RawData[Supplier name],A7,RawData[Lead time]) -> 20.133333 | D7: =AVERAGEIF(RawData[Supplier name],A7,RawData[Manufacturing lead time]) -> 14.933333 | E7: =AVERAGEIF(RawData[Supplier name],A7,RawData[Manufacturing costs]) -> 43.634121 | F7: =AVERAGEIF(RawData[Supplier name],A7,RawData[Defect rates])/100 -> 0.0002465786 | G7: =SUMIF(RawData[Supplier name],A7,RawData[Production volumes]) -> 7997 | H7: =COUNTIFS(RawData[Supplier name],A7,RawData[Inspection results],"Pass")/COUNTIF(RawData[Supplier name],A7) -> 0.13333333 | I7: =COUNTIFS(RawData[Supplier name],A7,RawData[Inspection results],"Fail")/COUNTIF(RawData[Supplier name],A7) -> 0.2 | K7: F5 | L7: =AVERAGEIF(RawData[Supplier name], A5, RawData[Defect rates]) / 100 -> 0.00018036297
A8: Supplier 4 | B8: =COUNTIF(RawData[Supplier name],A8) -> 18 | C8: =AVERAGEIF(RawData[Supplier name],A8,RawData[Lead time]) -> 15.222222 | D8: =AVERAGEIF(RawData[Supplier name],A8,RawData[Manufacturing lead time]) -> 15.333333 | E8: =AVERAGEIF(RawData[Supplier name],A8,RawData[Manufacturing costs]) -> 62.709727 | F8: =AVERAGEIF(RawData[Supplier name],A8,RawData[Defect rates])/100 -> 0.00023373974 | G8: =SUMIF(RawData[Supplier name],A8,RawData[Production volumes]) -> 11756 | H8: =COUNTIFS(RawData[Supplier name],A8,RawData[Inspection results],"Pass")/COUNTIF(RawData[Supplier name],A8) -> 0 | I8: =COUNTIFS(RawData[Supplier name],A8,RawData[Inspection results],"Fail")/COUNTIF(RawData[Supplier name],A8) -> 0.66666667 | K8: G5 | L8: =SUMIF(RawData[Supplier name], A5, RawData[Production volumes]) -> 13545
A9: Supplier 5 | B9: =COUNTIF(RawData[Supplier name],A9) -> 18 | C9: =AVERAGEIF(RawData[Supplier name],A9,RawData[Lead time]) -> 18.055556 | D9: =AVERAGEIF(RawData[Supplier name],A9,RawData[Manufacturing lead time]) -> 16.333333 | E9: =AVERAGEIF(RawData[Supplier name],A9,RawData[Manufacturing costs]) -> 44.768243 | F9: =AVERAGEIF(RawData[Supplier name],A9,RawData[Defect rates])/100 -> 0.00026654083 | G9: =SUMIF(RawData[Supplier name],A9,RawData[Production volumes]) -> 9381 | H9: =COUNTIFS(RawData[Supplier name],A9,RawData[Inspection results],"Pass")/COUNTIF(RawData[Supplier name],A9) -> 0.16666667 | I9: =COUNTIFS(RawData[Supplier name],A9,RawData[Inspection results],"Fail")/COUNTIF(RawData[Supplier name],A9) -> 0.38888889 | K9: H5 | L9: =COUNTIFS(RawData[Supplier name],A5,RawData[Inspection results],"Pass")/COUNTIF(RawData[Supplier name],A5) -> 0.48148148
A10: TOTAL / AVG | B10: =SUM(B5:B9) -> 100 | C10: =AVERAGE(C5:C9) -> 17.346869 | D10: =AVERAGE(D5:D9) -> 14.9567 | E10: =AVERAGE(E5:E9) -> 47.597727 | F10: =AVERAGE(F5:F9) -> 0.00023269943 | G10: =SUM(G5:G9) -> 56784 | H10: =AVERAGE(H5:H9) -> 0.20175084 | I10: =AVERAGE(I5:I9) -> 0.36828283 | K10: I5 | L10: =COUNTIFS(RawData[Supplier name],A5,RawData[Inspection results],"Fail")/COUNTIF(RawData[Supplier name],A5) -> 0.22222222

Sheet Logistics & Shipping
A1: Logistics & Shipping Analysis
A2: Formulas: COUNTIF | AVERAGEIF | SUMIF across three dimension slices: Carrier, Mode, Route
M3: Formula Reference
A4: By Carrier | G4: By Transport Mode | M4: B6 (carrier) | N4: =COUNTIF(RawData[Shipping carriers], A6) -> 28
A5: Carrier | B5: Shipments | C5: Avg Ship Time (days) | D5: Avg Ship Cost ($) | E5: Total Ship Cost ($) | G5: Mode | H5: Shipments | I5: Avg Total Cost ($) | J5: Total Cost ($) | K5: Avg Defect Rate (%) | M5: C6 | N5: =AVERAGEIF(RawData[Shipping carriers], A6, RawData[Shipping times]) -> 6.1428571
A6: Carrier A | B6: =COUNTIF(RawData[Shipping carriers],A6) -> 28 | C6: =AVERAGEIF(RawData[Shipping carriers],A6,RawData[Shipping times]) -> 6.1428571 | D6: =AVERAGEIF(RawData[Shipping carriers],A6,RawData[Shipping costs]) -> 5.5549225 | E6: =SUMIF(RawData[Shipping carriers],A6,RawData[Shipping costs]) -> 155.53783 | G6: Air | H6: =COUNTIF(RawData[Transportation modes],G6) -> 26 | I6: =AVERAGEIF(RawData[Transportation modes],G6,RawData[Costs]) -> 561.7126 | J6: =SUMIF(RawData[Transportation modes],G6,RawData[Costs]) -> 14604.527 | K6: =AVERAGEIF(RawData[Transportation modes],G6,RawData[Defect rates])/100 -> 0.00018239235 | M6: D6 | N6: =AVERAGEIF(RawData[Shipping carriers], A6, RawData[Shipping costs]) -> 5.5549225
A7: Carrier B | B7: =COUNTIF(RawData[Shipping carriers],A7) -> 43 | C7: =AVERAGEIF(RawData[Shipping carriers],A7,RawData[Shipping times]) -> 5.3023256 | D7: =AVERAGEIF(RawData[Shipping carriers],A7,RawData[Shipping costs]) -> 5.509247 | E7: =SUMIF(RawData[Shipping carriers],A7,RawData[Shipping costs]) -> 236.89762 | G7: Rail | H7: =COUNTIF(RawData[Transportation modes],G7) -> 28 | I7: =AVERAGEIF(RawData[Transportation modes],G7,RawData[Costs]) -> 541.74756 | J7: =SUMIF(RawData[Transportation modes],G7,RawData[Costs]) -> 15168.932 | K7: =AVERAGEIF(RawData[Transportation modes],G7,RawData[Defect rates])/100 -> 0.00023188139 | M7: E6 | N7: =SUMIF(RawData[Shipping carriers], A6, RawData[Shipping costs]) -> 155.53783
A8: Carrier C | B8: =COUNTIF(RawData[Shipping carriers],A8) -> 29 | C8: =AVERAGEIF(RawData[Shipping carriers],A8,RawData[Shipping times]) -> 6.0344828 | D8: =AVERAGEIF(RawData[Shipping carriers],A8,RawData[Shipping costs]) -> 5.5992916 | E8: =SUMIF(RawData[Shipping carriers],A8,RawData[Shipping costs]) -> 162.37946 | G8: Road | H8: =COUNTIF(RawData[Transportation modes],G8) -> 29 | I8: =AVERAGEIF(RawData[Transportation modes],G8,RawData[Costs]) -> 553.38599 | J8: =SUMIF(RawData[Transportation modes],G8,RawData[Costs]) -> 16048.194 | K8: =AVERAGEIF(RawData[Transportation modes],G8,RawData[Defect rates])/100 -> 0.00026209385 | M8: I6 (mode) | N8: =AVERAGEIF(RawData[Transportation modes], G6, RawData[Costs]) -> 561.7126
A9: TOTAL / AVG | B9: =SUM(B6:B8) -> 100 | C9: =AVERAGE(C6:C8) -> 5.8265552 | D9: =AVERAGE(D6:D8) -> 5.554487 | E9: =SUM(E6:E8) -> 554.81491 | G9: Sea | H9: =COUNTIF(RawData[Transportation modes],G9) -> 17 | I9: =AVERAGEIF(RawData[Transportation modes],G9,RawData[Costs]) -> 417.81915 | J9: =SUMIF(RawData[Transportation modes],G9,RawData[Costs]) -> 7102.9255 | K9: =AVERAGEIF(RawData[Transportation modes],G9,RawData[Defect rates])/100 -> 0.00023152813 | M9: K6 | N9: =AVERAGEIF(RawData[Transportation modes], G6, RawData[Defect rates]) / 100 -> 0.00018239235
G10: TOTAL / AVG | H10: =SUM(H6:H9) -> 100 | I10: =AVERAGE(I6:I9) -> 518.66632 | J10: =SUM(J6:J9) -> 52924.578 | K10: =AVERAGE(K6:K9) -> 0.00022697393 | M10: E14 (route) | N10: SUMIF(RawData[Routes],A14,RawData[Costs])/D14 <- Cost:Revenue
A12: By Route
A13: Route | B13: Shipments | C13: Avg Cost ($) | D13: Total Revenue ($) | E13: Cost-to-Revenue Ratio
A14: Route A | B14: =COUNTIF(RawData[Routes],A14) -> 43 | C14: =AVERAGEIF(RawData[Routes],A14,RawData[Costs]) -> 485.48313 | D14: =SUMIF(RawData[Routes],A14,RawData[Revenue generated]) -> 253198.85 | E14: =SUMIF(RawData[Routes],A14,RawData[Costs])/D14 -> 0.08244814
A15: Route B | B15: =COUNTIF(RawData[Routes],A15) -> 37 | C15: =AVERAGEIF(RawData[Routes],A15,RawData[Costs]) -> 595.65903 | D15: =SUMIF(RawData[Routes],A15,RawData[Revenue generated]) -> 204484.01 | E15: =SUMIF(RawData[Routes],A15,RawData[Costs])/D15 -> 0.10778048
A16: Route C | B16: =COUNTIF(RawData[Routes],A16) -> 20 | C16: =AVERAGEIF(RawData[Routes],A16,RawData[Costs]) -> 500.47098 | D16: =SUMIF(RawData[Routes],A16,RawData[Revenue generated]) -> 119921.96 | E16: =SUMIF(RawData[Routes],A16,RawData[Costs])/D16 -> 0.083466113
A17: TOTAL / AVG | B17: =SUM(B14:B16) -> 100 | C17: =AVERAGE(C14:C16) -> 527.20438 | D17: =SUM(D14:D16) -> 577604.82 | E17: =AVERAGE(E14:E16) -> 0.091231577

Sheet Location & Inventory
A1: Location & Inventory Performance
A2: Formulas: SUMIF | AVERAGEIF | COUNTIF — Note: 'Lead times' = operational; 'Lead time' = supplier
K3: Formula Reference
A4: Location | B4: SKUs | C4: Avg Stock Level | D4: Avg Availability (%) | E4: Avg Lead Time (days) | F4: Total Revenue ($) | G4: Avg Order Qty | H4: Stock-to-Order Ratio | I4: Revenue per SKU ($) | K4: B5 | L4: =COUNTIF(RawData[Location], A5) -> 18
A5: Bangalore | B5: =COUNTIF(RawData[Location],A5) -> 18 | C5: =AVERAGEIF(RawData[Location],A5,RawData[Stock levels]) -> 47.555556 | D5: =AVERAGEIF(RawData[Location],A5,RawData[Availability])/100 -> 0.56222222 | E5: =AVERAGEIF(RawData[Location],A5,RawData[Lead times]) -> 15.333333 | F5: =SUMIF(RawData[Location],A5,RawData[Revenue generated]) -> 102601.72 | G5: =AVERAGEIF(RawData[Location],A5,RawData[Order quantities]) -> 42.722222 | H5: =IFERROR(C5/G5,"-") -> 1.1131339 | I5: =IFERROR(F5/B5,"-") -> 5700.0958 | K5: C5 | L5: =AVERAGEIF(RawData[Location], A5, RawData[Stock levels]) -> 47.555556
A6: Chennai | B6: =COUNTIF(RawData[Location],A6) -> 20 | C6: =AVERAGEIF(RawData[Location],A6,RawData[Stock levels]) -> 39.95 | D6: =AVERAGEIF(RawData[Location],A6,RawData[Availability])/100 -> 0.548 | E6: =AVERAGEIF(RawData[Location],A6,RawData[Lead times]) -> 17.15 | F6: =SUMIF(RawData[Location],A6,RawData[Revenue generated]) -> 119142.82 | G6: =AVERAGEIF(RawData[Location],A6,RawData[Order quantities]) -> 55.45 | H6: =IFERROR(C6/G6,"-") -> 0.72046889 | I6: =IFERROR(F6/B6,"-") -> 5957.1408 | K6: D5 | L6: =AVERAGEIF(RawData[Location], A5, RawData[Availability]) / 100 -> 0.56222222
A7: Delhi | B7: =COUNTIF(RawData[Location],A7) -> 15 | C7: =AVERAGEIF(RawData[Location],A7,RawData[Stock levels]) -> 50.066667 | D7: =AVERAGEIF(RawData[Location],A7,RawData[Availability])/100 -> 0.494 | E7: =AVERAGEIF(RawData[Location],A7,RawData[Lead times]) -> 17.666667 | F7: =SUMIF(RawData[Location],A7,RawData[Revenue generated]) -> 81027.701 | G7: =AVERAGEIF(RawData[Location],A7,RawData[Order quantities]) -> 48.866667 | H7: =IFERROR(C7/G7,"-") -> 1.0245566 | I7: =IFERROR(F7/B7,"-") -> 5401.8467 | K7: E5 | L7: AVERAGEIF(RawData[Location],A5,RawData[Lead times])
A8: Kolkata | B8: =COUNTIF(RawData[Location],A8) -> 25 | C8: =AVERAGEIF(RawData[Location],A8,RawData[Stock levels]) -> 57.56 | D8: =AVERAGEIF(RawData[Location],A8,RawData[Availability])/100 -> 0.4084 | E8: =AVERAGEIF(RawData[Location],A8,RawData[Lead times]) -> 15.92 | F8: =SUMIF(RawData[Location],A8,RawData[Revenue generated]) -> 137077.55 | G8: =AVERAGEIF(RawData[Location],A8,RawData[Order quantities]) -> 49.12 | H8: =IFERROR(C8/G8,"-") -> 1.1718241 | I8: =IFERROR(F8/B8,"-") -> 5483.102 | K8: F5 | L8: =SUMIF(RawData[Location], A5, RawData[Revenue generated]) -> 102601.72
A9: Mumbai | B9: =COUNTIF(RawData[Location],A9) -> 22 | C9: =AVERAGEIF(RawData[Location],A9,RawData[Stock levels]) -> 42.363636 | D9: =AVERAGEIF(RawData[Location],A9,RawData[Availability])/100 -> 0.44090909 | E9: =AVERAGEIF(RawData[Location],A9,RawData[Lead times]) -> 14.272727 | F9: =SUMIF(RawData[Location],A9,RawData[Revenue generated]) -> 137755.03 | G9: =AVERAGEIF(RawData[Location],A9,RawData[Order quantities]) -> 49.227273 | H9: =IFERROR(C9/G9,"-") -> 0.86057248 | I9: =IFERROR(F9/B9,"-") -> 6261.5921 | K9: H5 (derived) | L9: IFERROR(C5/G5,"-") <- Stock / Order Qty
A10: TOTAL / AVG | B10: =SUM(B5:B9) -> 100 | C10: =AVERAGE(C5:C9) -> 47.499172 | D10: =AVERAGE(D5:D9) -> 0.49070626 | E10: =AVERAGE(E5:E9) -> 16.068545 | F10: =SUM(F5:F9) -> 577604.82 | G10: =AVERAGE(G5:G9) -> 49.077232 | H10: =IFERROR(AVERAGE(C5:C9)/AVERAGE(G5:G9),"-") -> 0.96784536 | I10: =IFERROR(F10/B10,"-") -> 5776.0482 | K10: I5 (derived) | L10: IFERROR(F5/B5,"-") <- Revenue / SKU count

Sheet Quality & Defects
A1: Quality Control & Defect Analysis
A2: Formulas: AVERAGEIF | COUNTIFS (two criteria: dimension + inspection result) | Derived: Pass Rate, Fail Rate, Pending Rate
K3: Formula Reference
A4: By Product Type | K4: B6 | L4: =AVERAGEIF(RawData[Product type], A6, RawData[Defect rates]) / 100 -> 0.0001919287
A5: Product Type | B5: Avg Defect Rate (%) | C5: Pass | D5: Fail | E5: Pending | F5: Total SKUs | G5: Pass Rate (%) | H5: Fail Rate (%) | I5: Pending Rate (%) | K5: C6 (Pass) | L5: =COUNTIFS(RawData[Product type], A6, RawData[Inspection results], "Pass") -> 6
A6: cosmetics | B6: =AVERAGEIF(RawData[Product type],A6,RawData[Defect rates])/100 -> 0.0001919287 | C6: =COUNTIFS(RawData[Product type],A6,RawData[Inspection results],"Pass") -> 6 | D6: =COUNTIFS(RawData[Product type],A6,RawData[Inspection results],"Fail") -> 10 | E6: =COUNTIFS(RawData[Product type],A6,RawData[Inspection results],"Pending") -> 10 | F6: =C6+D6+E6 -> 26 | G6: =IFERROR(C6/F6,0) -> 0.23076923 | H6: =IFERROR(D6/F6,0) -> 0.38461538 | I6: =IFERROR(E6/F6,0) -> 0.38461538 | K6: D6 (Fail) | L6: =COUNTIFS(RawData[Product type], A6, RawData[Inspection results], "Fail") -> 10
A7: haircare | B7: =AVERAGEIF(RawData[Product type],A7,RawData[Defect rates])/100 -> 0.00024831502 | C7: =COUNTIFS(RawData[Product type],A7,RawData[Inspection results],"Pass") -> 6 | D7: =COUNTIFS(RawData[Product type],A7,RawData[Inspection results],"Fail") -> 13 | E7: =COUNTIFS(RawData[Product type],A7,RawData[Inspection results],"Pending") -> 15 | F7: =C7+D7+E7 -> 34 | G7: =IFERROR(C7/F7,0) -> 0.17647059 | H7: =IFERROR(D7/F7,0) -> 0.38235294 | I7: =IFERROR(E7/F7,0) -> 0.44117647 | K7: E6 (Pending) | L7: =COUNTIFS(RawData[Product type], A6, RawData[Inspection results], "Pending") -> 10
A8: skincare | B8: =AVERAGEIF(RawData[Product type],A8,RawData[Defect rates])/100 -> 0.00023346808 | C8: =COUNTIFS(RawData[Product type],A8,RawData[Inspection results],"Pass") -> 11 | D8: =COUNTIFS(RawData[Product type],A8,RawData[Inspection results],"Fail") -> 13 | E8: =COUNTIFS(RawData[Product type],A8,RawData[Inspection results],"Pending") -> 16 | F8: =C8+D8+E8 -> 40 | G8: =IFERROR(C8/F8,0) -> 0.275 | H8: =IFERROR(D8/F8,0) -> 0.325 | I8: =IFERROR(E8/F8,0) -> 0.4 | K8: F6 (Total) | L8: =C6 + D6 + E6 -> 26
A9: TOTAL / AVG | B9: =AVERAGE(B6:B8) -> 0.0002245706 | C9: =SUM(C6:C8) -> 23 | D9: =SUM(D6:D8) -> 36 | E9: =SUM(E6:E8) -> 41 | F9: =SUM(F6:F8) -> 100 | G9: =IFERROR(C9/F9,0) -> 0.23 | H9: =IFERROR(D9/F9,0) -> 0.36 | I9: =IFERROR(E9/F9,0) -> 0.41 | K9: G6 (Pass%) | L9: =IFERROR(C6 / F6, 0) -> 0.23076923
K10: H6 (Fail%) | L10: =IFERROR(D6 / F6, 0) -> 0.38461538
A11: By Supplier | K11: Supplier rows | L11: Same pattern — replace [Product type] with [Supplier name]
A12: Supplier | B12: Avg Defect Rate (%) | C12: Pass | D12: Fail | E12: Pending | F12: Total SKUs | G12: Pass Rate (%) | H12: Fail Rate (%) | I12: Pending Rate (%)
A13: Supplier 1 | B13: =AVERAGEIF(RawData[Supplier name],A13,RawData[Defect rates])/100 -> 0.00018036297 | C13: =COUNTIFS(RawData[Supplier name],A13,RawData[Inspection results],"Pass") -> 13 | D13: =COUNTIFS(RawData[Supplier name],A13,RawData[Inspection results],"Fail") -> 6 | E13: =COUNTIFS(RawData[Supplier name],A13,RawData[Inspection results],"Pending") -> 8 | F13: =C13+D13+E13 -> 27 | G13: =IFERROR(C13/F13,0) -> 0.48148148 | H13: =IFERROR(D13/F13,0) -> 0.22222222 | I13: =IFERROR(E13/F13,0) -> 0.2962963
A14: Supplier 2 | B14: =AVERAGEIF(RawData[Supplier name],A14,RawData[Defect rates])/100 -> 0.00023627501 | C14: =COUNTIFS(RawData[Supplier name],A14,RawData[Inspection results],"Pass") -> 5 | D14: =COUNTIFS(RawData[Supplier name],A14,RawData[Inspection results],"Fail") -> 8 | E14: =COUNTIFS(RawData[Supplier name],A14,RawData[Inspection results],"Pending") -> 9 | F14: =C14+D14+E14 -> 22 | G14: =IFERROR(C14/F14,0) -> 0.22727273 | H14: =IFERROR(D14/F14,0) -> 0.36363636 | I14: =IFERROR(E14/F14,0) -> 0.40909091
A15: Supplier 3 | B15: =AVERAGEIF(RawData[Supplier name],A15,RawData[Defect rates])/100 -> 0.0002465786 | C15: =COUNTIFS(RawData[Supplier name],A15,RawData[Inspection results],"Pass") -> 2 | D15: =COUNTIFS(RawData[Supplier name],A15,RawData[Inspection results],"Fail") -> 3 | E15: =COUNTIFS(RawData[Supplier name],A15,RawData[Inspection results],"Pending") -> 10 | F15: =C15+D15+E15 -> 15 | G15: =IFERROR(C15/F15,0) -> 0.13333333 | H15: =IFERROR(D15/F15,0) -> 0.2 | I15: =IFERROR(E15/F15,0) -> 0.66666667
A16: Supplier 4 | B16: =AVERAGEIF(RawData[Supplier name],A16,RawData[Defect rates])/100 -> 0.00023373974 | C16: =COUNTIFS(RawData[Supplier name],A16,RawData[Inspection results],"Pass") -> 0 | D16: =COUNTIFS(RawData[Supplier name],A16,RawData[Inspection results],"Fail") -> 12 | E16: =COUNTIFS(RawData[Supplier name],A16,RawData[Inspection results],"Pending") -> 6 | F16: =C16+D16+E16 -> 18 | G16: =IFERROR(C16/F16,0) -> 0 | H16: =IFERROR(D16/F16,0) -> 0.66666667 | I16: =IFERROR(E16/F16,0) -> 0.33333333
A17: Supplier 5 | B17: =AVERAGEIF(RawData[Supplier name],A17,RawData[Defect rates])/100 -> 0.00026654083 | C17: =COUNTIFS(RawData[Supplier name],A17,RawData[Inspection results],"Pass") -> 3 | D17: =COUNTIFS(RawData[Supplier name],A17,RawData[Inspection results],"Fail") -> 7 | E17: =COUNTIFS(RawData[Supplier name],A17,RawData[Inspection results],"Pending") -> 8 | F17: =C17+D17+E17 -> 18 | G17: =IFERROR(C17/F17,0) -> 0.16666667 | H17: =IFERROR(D17/F17,0) -> 0.38888889 | I17: =IFERROR(E17/F17,0) -> 0.44444444
A18: TOTAL / AVG | B18: =AVERAGE(B13:B17) -> 0.00023269943 | C18: =SUM(C13:C17) -> 23 | D18: =SUM(D13:D17) -> 36 | E18: =SUM(E13:E17) -> 41 | F18: =SUM(F13:F17) -> 100 | G18: =IFERROR(C18/F18,0) -> 0.23 | H18: =IFERROR(D18/F18,0) -> 0.36 | I18: =IFERROR(E18/F18,0) -> 0.41

Sheet KPI Report Template
A1: SUPPLY CHAIN KPI DASHBOARD
A2: Reporting Period: [Enter Period] | Prepared by: [Name] | Date: [DD/MM/YYYY]
A4: Total Revenue | D4: Total Units Sold | G4: Overall Defect Rate | J4: Overall Pass Rate
A5: ='Revenue by Product'!D8 -> 577604.82 | D5: ='Revenue by Product'!C8 -> 46099 | G5: ='Quality & Defects'!B9 -> 0.0002245706 | J5: ='Quality & Defects'!G9 -> 0.23
A6: ▲ vs prior period | D6: ▲ vs prior period | G6: ▲ vs prior period | J6: ▲ vs prior period
A8: Key Performance Indicators — Live formulas linked to analysis sheets
A9: KPI | B9: Category | C9: Formula / Source | D9: Current Value | E9: Target | F9: Status | G9: Notes
A10: Total Revenue ($) | B10: Financial | C10: ='Revenue by Product'!D8 -> 577604.82 | D10: ='Revenue by Product'!D8 -> 577604.82 | E10: $900,000 | F10: ✓ On Track
A11: Revenue per SKU ($) | B11: Financial | C11: Revenue / SKU count (live: Revenue by Product D8 / B8) | D11: ='Revenue by Product'!D8/'Revenue by Product'!B8 -> 5776.0482 | E11: $8,500 | F11: ✓ On Track
A12: Units Sold | B12: Sales | C12: ='Revenue by Product'!C8 -> 46099 | D12: ='Revenue by Product'!C8 -> 46099 | E12: 80,000 | F12: ● Monitor
A13: Avg Selling Price ($) | B13: Sales | C13: =AVERAGE(RawData[Price]) -> 49.462461 | D13: =AVERAGE(RawData[Price]) -> 49.462461 | E13: $50.00 | F13: ● Monitor | G13: Price variance vs target
A14: Avg Stock Level | B14: Inventory | C14: =AVERAGE(RawData[Stock levels]) -> 47.77 | D14: =AVERAGE(RawData[Stock levels]) -> 47.77 | E14: 50+ | F14: ⚠ Below Target | G14: Review reorder points
A15: Avg Availability (%) | B15: Inventory | C15: =AVERAGE(RawData[Availability])/100 -> 0.484 | D15: =AVERAGE(RawData[Availability])/100 -> 0.484 | E15: 60% | F15: ⚠ Below Target | G15: Low availability flagged
A16: Avg Order Quantity | B16: Procurement | C16: =AVERAGE(RawData[Order quantities]) -> 49.22 | D16: =AVERAGE(RawData[Order quantities]) -> 49.22 | E16: 60 | F16: ● Monitor
A17: Avg Lead Time (days) | B17: Procurement | C17: =AVERAGE(RawData[Lead times]) -> 15.96 | D17: =AVERAGE(RawData[Lead times]) -> 15.96 | E17: 15 | F17: ⚠ Above Target | G17: Lead time optimisation needed
A18: Avg Shipping Time (days) | B18: Logistics | C18: ='Logistics & Shipping'!C9 -> 5.8265552 | D18: ='Logistics & Shipping'!C9 -> 5.8265552 | E18: 4 | F18: ✓ On Track
A19: Avg Shipping Cost ($) | B19: Logistics | C19: ='Logistics & Shipping'!D9 -> 5.554487 | D19: ='Logistics & Shipping'!D9 -> 5.554487 | E19: $8.00 | F19: ✓ On Track
A20: Avg Defect Rate (%) | B20: Quality | C20: ='Quality & Defects'!B9 -> 0.0002245706 | D20: ='Quality & Defects'!B9 -> 0.0002245706 | E20: <2% | F20: ⚠ Above Target | G20: Review Supplier 2 & Supplier 4
A21: Inspection Pass Rate (%) | B21: Quality | C21: ='Quality & Defects'!G9 -> 0.23 | D21: ='Quality & Defects'!G9 -> 0.23 | E21: 40% | F21: ⚠ Below Target | G21: Only 23% passing — critical
A22: Avg Mfg Cost ($) | B22: Operations | C22: =AVERAGE(RawData[Manufacturing costs]) -> 47.266693 | D22: =AVERAGE(RawData[Manufacturing costs]) -> 47.266693 | E22: $40.00 | F22: ● Monitor
A23: Avg Mfg Lead Time (days) | B23: Operations | C23: =AVERAGE(RawData[Manufacturing lead time]) -> 14.77 | D23: =AVERAGE(RawData[Manufacturing lead time]) -> 14.77 | E23: 20 | F23: ✓ On Track
A25: KEY FINDINGS & RECOMMENDATIONS
A26: 1. QUALITY — Inspection pass rate critically low (23%). Audit all suppliers; Supplier 2 & 4 show highest defect rates.
A27: 2. INVENTORY — Avg availability (48%) and stock (48 units) below targets. Review safety stock levels and reorder points.
A28: 3. LEAD TIMES — Avg lead time 17.9 days exceeds 15-day target. Renegotiate with Supplier 3 or qualify backup suppliers.
A29: 4. LOGISTICS — Air transport carries highest cost. Evaluate shifting Air volume to Road/Rail where SLAs allow.
A30: 5. REVENUE — Skincare leads revenue (40 SKUs). Prioritise stock and quality investment in this product line.

Sheet Monthly Report Template
A1: SUPPLY CHAIN MONTHLY REPORT
A2: Month: [MONTH YEAR] | Prepared by: [NAME] | Date: [DD/MM/YYYY]
A4: 1. EXECUTIVE SUMMARY
A5: Provide a 3–5 sentence overview of supply chain performance for the period.
A9: 2. REVENUE & SALES
A10: Metric | B10: Prior Period | C10: This Period | D10: Target | E10: Variance | F10: Status
E11: =IFERROR(C11-B11,"") -> 0
E12: =IFERROR(C12-B12,"") -> 0
E13: =IFERROR(C13-B13,"") -> 0
E14: =IFERROR(C14-B14,"") -> 0
A15: 3. INVENTORY & STOCK
A16: Metric | B16: Prior Period | C16: This Period | D16: Target | E16: Variance | F16: Status
E17: =IFERROR(C17-B17,"") -> 0
E18: =IFERROR(C18-B18,"") -> 0
E19: =IFERROR(C19-B19,"") -> 0
E20: =IFERROR(C20-B20,"") -> 0
A21: 4. QUALITY & DEFECTS
A22: Metric | B22: Prior Period | C22: This Period | D22: Target | E22: Variance | F22: Status
E23: =IFERROR(C23-B23,"") -> 0
E24: =IFERROR(C24-B24,"") -> 0
E25: =IFERROR(C25-B25,"") -> 0
E26: =IFERROR(C26-B26,"") -> 0
A27: 5. LOGISTICS & SHIPPING
A28: Metric | B28: Prior Period | C28: This Period | D28: Target | E28: Variance | F28: Status
E29: =IFERROR(C29-B29,"") -> 0
E30: =IFERROR(C30-B30,"") -> 0
E31: =IFERROR(C31-B31,"") -> 0
E32: =IFERROR(C32-B32,"") -> 0
A33: 6. SUPPLIER PERFORMANCE
A34: Metric | B34: Prior Period | C34: This Period | D34: Target | E34: Variance | F34: Status
E35: =IFERROR(C35-B35,"") -> 0
E36: =IFERROR(C36-B36,"") -> 0
E37: =IFERROR(C37-B37,"") -> 0
E38: =IFERROR(C38-B38,"") -> 0
A39: 7. ISSUES & RISKS
A40: List operational risks, supplier issues, or logistics disruptions observed this period.
A43: 8. ACTIONS & NEXT STEPS
A44: List agreed actions, owners, and due dates.
